snaphelpers/__init__.py
snaphelpers/_conf.py
snaphelpers/_ctl.py
snaphelpers/_env.py
snaphelpers/_health.py
snaphelpers/_hook.py
snaphelpers/_importlib.py
snaphelpers/_meta.py
snaphelpers/_path.py
snaphelpers/_service.py
snaphelpers/_snap.py
snaphelpers/py.typed
snaphelpers/scripts/__init__.py
snaphelpers/scripts/_script.py
snaphelpers/scripts/snap_helpers.py
snap_helpers-0.4.2.dist-info/LICENSE.txt
snap_helpers-0.4.2.dist-info/METADATA
snap_helpers-0.4.2.dist-info/WHEEL
snap_helpers-0.4.2.dist-info/entry_points.txt
snap_helpers-0.4.2.dist-info/top_level.txt
snap_helpers-0.4.2.dist-info/RECORD
