Metadata-Version: 2.1
Name: snap-helpers
Version: 0.4.2
Summary: Helpers for interacting with the Snap system within a Snap
Author-email: Alberto Donato <alberto.donato@gmail.com>
Maintainer-email: Alberto Donato <alberto.donato@gmail.com>
License: GNU LESSER GENERAL PUBLIC LICENSE
Project-URL: changelog, https://github.com/albertodonato/snap-helpers/blob/main/CHANGES.rst
Project-URL: documentation, https://readthedocs.org/projects/snap-helpers/
Project-URL: homepage, https://github.com/albertodonato/snap-helpers
Project-URL: repository, https://github.com/albertodonato/snap-helpers
Keywords: snap,snapcraft,snappy
Classifier: Development Status :: 4 - Beta
Classifier: License :: OSI Approved :: GNU Lesser General Public License v3 or later (LGPLv3+)
Classifier: Operating System :: POSIX :: Linux
Classifier: Programming Language :: Python :: 3 :: Only
Classifier: Programming Language :: Python :: 3.8
Classifier: Programming Language :: Python :: 3.9
Classifier: Programming Language :: Python :: 3.10
Classifier: Programming Language :: Python :: 3.11
Classifier: Topic :: System :: Archiving :: Packaging
Classifier: Topic :: System :: Software Distribution
Requires-Python: >=3.8
License-File: LICENSE.txt
Requires-Dist: PyYAML
Requires-Dist: importlib-metadata ; python_version < "3.10"
Provides-Extra: testing
Requires-Dist: pytest ; extra == 'testing'
Requires-Dist: pytest-mock ; extra == 'testing'
